pyutmodel/DisplayMethodParameters.py
pyutmodel/ModelTypes.py
pyutmodel/PyutActor.py
pyutmodel/PyutClass.py
pyutmodel/PyutClassCommon.py
pyutmodel/PyutDisplayParameters.py
pyutmodel/PyutField.py
pyutmodel/PyutInterface.py
pyutmodel/PyutLink.py
pyutmodel/PyutLinkType.py
pyutmodel/PyutLinkedObject.py
pyutmodel/PyutMethod.py
pyutmodel/PyutModifier.py
pyutmodel/PyutNote.py
pyutmodel/PyutObject.py
pyutmodel/PyutParameter.py
pyutmodel/PyutSDInstance.py
pyutmodel/PyutSDMessage.py
pyutmodel/PyutStereotype.py
pyutmodel/PyutText.py
pyutmodel/PyutType.py
pyutmodel/PyutUseCase.py
pyutmodel/PyutVisibilityEnum.py
pyutmodel/__init__.py
pyutmodel/_version.py
pyutmodel/py.typed
pyutmodel-1.5.1.dist-info/LICENSE
pyutmodel-1.5.1.dist-info/METADATA
pyutmodel-1.5.1.dist-info/WHEEL
pyutmodel-1.5.1.dist-info/top_level.txt
pyutmodel-1.5.1.dist-info/RECORD
