Metadata-Version: 2.1
Name: pyutmodel
Version: 1.5.1
Summary: External Pyut Data Model
Author-email: "Humberto A. Sanchez II" <Humbert.A.Sanchez.II@gmail.com>
Maintainer-email: "Humberto A. Sanchez II" <Humbert.A.Sanchez.II@gmail.com>
License: GNU AFFERO GENERAL PUBLIC LICENSE
Project-URL: Repository, https://github.com/hasii2011/pyutmodel
Keywords: pyut,external model,python
License-File: LICENSE
Requires-Dist: codeallybasic ==0.5.2
Requires-Dist: Deprecated ==1.2.14
